tarmtexract/__init__.py
tarmtexract/lambda_function.py
tarmtextract-0.0.11.dist-info/METADATA
tarmtextract-0.0.11.dist-info/WHEEL
tarmtextract-0.0.11.dist-info/top_level.txt
tarmtextract-0.0.11.dist-info/RECORD
