Metadata-Version: 2.1
Name: tarmtextract
Version: 0.0.11
Summary: A package that allows to extract text from pdf/word file which is save in aws s3
Home-page: UNKNOWN
Author: Paras Deshbhratar
Author-email: <paras.d13@gmail.com>
License: UNKNOWN
Keywords: python,textract,pdfplumber,textextractor
Platform: UNKNOWN
Classifier: Development Status :: 1 - Planning
Classifier: Intended Audience :: Developers
Classifier: Programming Language :: Python :: 3
Classifier: Operating System :: Unix
Classifier: Operating System :: MacOS :: MacOS X
Classifier: Operating System :: Microsoft :: Windows
Requires-Dist: pdfplumber
Requires-Dist: textract
Requires-Dist: boto3
